{
    "name": "MNCCanineLeitoCanineBJ",
    "modpack": "MNCCreatures",
    "length": 2,
    "navigations": [
        {
            "destination": "MNCCanineLeitoCanineBJ-3",
            "description": "Next",
            "icon": "OStim/symbols/next"
        },
        {
            "destination": "MNCCanineLeitoCanineBJ-1",
            "description": "Return",
            "icon": "OStim/symbols/return"
        },
        {
            "destination": "MNCCanineHubFM",
            "description": "Return to Hub",
            "icon": "OCreatures/canine/canine"
        }
    ],
    "speeds": [
        {
            "animation": "MNCleitoCaninebj_S2"
        }
    ],
    "actors": [
        {
            "type": "crcanine",
            "intendedSex": "male",
            "requirements": [
                "penis"
            ],
            "tags": [
                "standing"
            ]
        },
        {
            "intendedSex": "female",
            "tags": [
                "lyingfront"
            ]
        }
    ],
    "actions": [
        {
            "type": "blowjob",
            "actor": 1,
            "target": 0
        }
    ],
    "tags": [
        "mnc",
        "creature",
        "canine"
    ]
}