{
    "name": "Billyy Canine Below Blowjob",
    "modpack": "BillyyCreatures",
    "length": 2,
    "navigations": [
        {
            "destination": "BillyyCanineBelowBlowjob-5",
            "description": "Next (Climax)",
            "icon": "OStim/symbols/climax"
        },
        {
            "destination": "BillyyCanineBelowBlowjob-3",
            "description": "Return",
            "icon": "OStim/symbols/return"
        },
        {
            "destination": "BillyyCanineHubFM",
            "description": "Return",
            "icon": "OCreatures/canine/canine"
        }
    ],
    "speeds": [
        {
            "animation": "B_Can_B_BlwBJ_S4"
        }
    ],
    "actors": [
        {
			"type": "crcanine",
            "intendedSex": "male",
			"autoTransitions": {
				"climax": "BillyyCanineBelowBlowjob-5"
			},
			"requirements": [
				"penis"
			],
            "tags": [
                "standing"
            ]
        },
        {
            "intendedSex": "female",
            "tags": [
                "lyingback"
            ]
        }
    ],
    "actions": [
        {
            "type": "deepthroat",
            "actor": 1,
            "target": 0,
			"performer": 0
        }
    ],
    "tags": [
        "billyy",
        "creature",
		"canine"
    ]
}