{
    "name": "BillyyRieklingFFCDoggyandBlowjob",
    "modpack": "BillyyCreatures",
    "length": 2,
    "navigations": [
        {
            "destination": "BillyyRieklingFFCDoggyandBlowjob-10",
            "description": "Next",
            "icon": "OStim/symbols/next"
        },
        {
            "destination": "BillyyRieklingFFCDoggyandBlowjob-8",
            "description": "Return",
            "icon": "OStim/symbols/return"
        },
        {
            "destination": "BillyyRieklingHubFFM",
            "description": "Return to Hub",
            "icon": "OCreatures/riekling/riekling"
        }
    ],
    "speeds": [
        {
            "animation": "B_Riek_B_FFCDogBJ_S9"
        }
    ],
    "actors": [
        {
			"type": "crRiekling",
            "intendedSex": "male",
			"animationIndex": 0,
			"requirements": [
				"penis"
			],
            "tags": [
                "standing"
            ]
        },
        {
            "intendedSex": "female",
			"animationIndex": 1,
            "tags": [
                "kneeling"
            ]
        },
		{
            "intendedSex": "female",
			"animationIndex": 2,
            "tags": [
                "lyingside"
            ]
        }
    ],
    "actions": [
        {
            "type": "blowjob",
            "actor": 1,
            "target": 0
        },
        {
            "type": "cunnilingus",
            "actor": 2,
            "target": 1
        },
		{
            "type": "holdinghip",
            "actor": 2,
            "target": 1
        }
    ],
    "tags": [
        "billyy",
        "creature",
        "riekling"
    ]
}